[
  {
    "surahNo": 76,
    "ayahNo": 6,
    "ayahArV1": "عَيْنًا يَشْرَبُ بِهَا عِبَادُ ٱللَّهِ يُفَجِّرُونَهَا تَفْجِيرًا",
    "ayahArV2": "عينا يشرب بها عباد الله يفجرونها تفجيرا",
    "ayahEn": "˹from˺ a spring where Allah’s servants will drink, flowing at their will.",
    "meta": {
      "page": 579,
      "juz": 29,
      "hizb": 58,
      "hizbQuarter": 231,
      "sajda": false
    }
  },
  {
    "surahNo": 76,
    "ayahNo": 7,
    "ayahArV1": "يُوفُونَ بِٱلنَّذْرِ وَيَخَافُونَ يَوْمًا كَانَ شَرُّهُۥ مُسْتَطِيرًا",
    "ayahArV2": "يوفون بالنذر ويخافون يوما كان شره مستطيرا",
    "ayahEn": "They ˹are those who˺ fulfil ˹their˺ vows and fear a Day of sweeping horror",
    "meta": {
      "page": 579,
      "juz": 29,
      "hizb": 58,
      "hizbQuarter": 231,
      "sajda": false
    }
  },
  {
    "surahNo": 76,
    "ayahNo": 8,
    "ayahArV1": "وَيُطْعِمُونَ ٱلطَّعَامَ عَلَىٰ حُبِّهِۦ مِسْكِينًا وَيَتِيمًا وَأَسِيرًا",
    "ayahArV2": "ويطعمون الطعام على حبه مسكينا ويتيما واسيرا",
    "ayahEn": "and give food—despite their desire for it—to the poor, the orphan, and the captive",
    "meta": {
      "page": 579,
      "juz": 29,
      "hizb": 58,
      "hizbQuarter": 231,
      "sajda": false
    }
  },
  {
    "surahNo": 76,
    "ayahNo": 9,
    "ayahArV1": "إِنَّمَا نُطْعِمُكُمْ لِوَجْهِ ٱللَّهِ لَا نُرِيدُ مِنكُمْ جَزَآءً وَلَا شُكُورًا",
    "ayahArV2": "انما نطعمكم لوجه الله لا نريد منكم جزاء ولا شكورا",
    "ayahEn": "˹saying to themselves,˺ “We feed you only for the sake of Allah, seeking neither reward nor thanks from you.",
    "meta": {
      "page": 579,
      "juz": 29,
      "hizb": 58,
      "hizbQuarter": 231,
      "sajda": false
    }
  },
  {
    "surahNo": 76,
    "ayahNo": 10,
    "ayahArV1": "إِنَّا نَخَافُ مِن رَّبِّنَا يَوْمًا عَبُوسًا قَمْطَرِيرًا",
    "ayahArV2": "انا نخاف من ربنا يوما عبوسا قمطريرا",
    "ayahEn": "We fear from our Lord a horribly distressful Day.”",
    "meta": {
      "page": 579,
      "juz": 29,
      "hizb": 58,
      "hizbQuarter": 231,
      "sajda": false
    }
  },
  {
    "surahNo": 76,
    "ayahNo": 11,
    "ayahArV1": "فَوَقَىٰهُمُ ٱللَّهُ شَرَّ ذَٰلِكَ ٱلْيَوْمِ وَلَقَّىٰهُمْ نَضْرَةً وَسُرُورًا",
    "ayahArV2": "فوقاهم الله شر ذلك اليوم ولقاهم نضرة وسرورا",
    "ayahEn": "So Allah will deliver them from the horror of that Day, and grant them radiance and joy",
    "meta": {
      "page": 579,
      "juz": 29,
      "hizb": 58,
      "hizbQuarter": 231,
      "sajda": false
    }
  },
  {
    "surahNo": 76,
    "ayahNo": 12,
    "ayahArV1": "وَجَزَىٰهُم بِمَا صَبَرُوا۟ جَنَّةً وَحَرِيرًا",
    "ayahArV2": "وجزاهم بما صبروا جنة وحريرا",
    "ayahEn": "and reward them for their perseverance with a Garden ˹in Paradise˺ and ˹garments of˺ silk.",
    "meta": {
      "page": 579,
      "juz": 29,
      "hizb": 58,
      "hizbQuarter": 231,
      "sajda": false
    }
  },
  {
    "surahNo": 76,
    "ayahNo": 13,
    "ayahArV1": "مُّتَّكِـِٔينَ فِيهَا عَلَى ٱلْأَرَآئِكِ ۖ لَا يَرَوْنَ فِيهَا شَمْسًا وَلَا زَمْهَرِيرًا",
    "ayahArV2": "متكئين فيها على الارائك لا يرون فيها شمسا ولا زمهريرا",
    "ayahEn": "There they will be reclining on ˹canopied˺ couches, never seeing scorching heat or bitter cold.",
    "meta": {
      "page": 579,
      "juz": 29,
      "hizb": 58,
      "hizbQuarter": 231,
      "sajda": false
    }
  },
  {
    "surahNo": 76,
    "ayahNo": 14,
    "ayahArV1": "وَدَانِيَةً عَلَيْهِمْ ظِلَـٰلُهَا وَذُلِّلَتْ قُطُوفُهَا تَذْلِيلًا",
    "ayahArV2": "ودانية عليهم ظلالها وذللت قطوفها تذليلا",
    "ayahEn": "The Garden’s shade will be right above them, and its fruit will be made very easy to reach.",
    "meta": {
      "page": 579,
      "juz": 29,
      "hizb": 58,
      "hizbQuarter": 231,
      "sajda": false
    }
  },
  {
    "surahNo": 76,
    "ayahNo": 15,
    "ayahArV1": "وَيُطَافُ عَلَيْهِم بِـَٔانِيَةٍ مِّن فِضَّةٍ وَأَكْوَابٍ كَانَتْ قَوَارِيرَا۠",
    "ayahArV2": "ويطاف عليهم بانية من فضة واكواب كانت قواريرا",
    "ayahEn": "They will be waited on with silver vessels and cups of crystal—",
    "meta": {
      "page": 579,
      "juz": 29,
      "hizb": 58,
      "hizbQuarter": 231,
      "sajda": false
    }
  },
  {
    "surahNo": 76,
    "ayahNo": 16,
    "ayahArV1": "قَوَارِيرَا۟ مِن فِضَّةٍ قَدَّرُوهَا تَقْدِيرًا",
    "ayahArV2": "قوارير من فضة قدروها تقديرا",
    "ayahEn": "crystalline silver, filled precisely as desired.",
    "meta": {
      "page": 579,
      "juz": 29,
      "hizb": 58,
      "hizbQuarter": 231,
      "sajda": false
    }
  },
  {
    "surahNo": 76,
    "ayahNo": 17,
    "ayahArV1": "وَيُسْقَوْنَ فِيهَا كَأْسًا كَانَ مِزَاجُهَا زَنجَبِيلًا",
    "ayahArV2": "ويسقون فيها كاسا كان مزاجها زنجبيلا",
    "ayahEn": "And they will be given a drink ˹of pure wine˺ flavoured with ginger",
    "meta": {
      "page": 579,
      "juz": 29,
      "hizb": 58,
      "hizbQuarter": 231,
      "sajda": false
    }
  },
  {
    "surahNo": 76,
    "ayahNo": 18,
    "ayahArV1": "عَيْنًا فِيهَا تُسَمَّىٰ سَلْسَبِيلًا",
    "ayahArV2": "عينا فيها تسمى سلسبيلا",
    "ayahEn": "from a spring there, called Salsabîl.",
    "meta": {
      "page": 579,
      "juz": 29,
      "hizb": 58,
      "hizbQuarter": 231,
      "sajda": false
    }
  },
  {
    "surahNo": 76,
    "ayahNo": 19,
    "ayahArV1": "۞ وَيَطُوفُ عَلَيْهِمْ وِلْدَٰنٌ مُّخَلَّدُونَ إِذَا رَأَيْتَهُمْ حَسِبْتَهُمْ لُؤْلُؤًا مَّنثُورًا",
    "ayahArV2": "ويطوف عليهم ولدان مخلدون اذا رايتهم حسبتهم لؤلؤا منثورا",
    "ayahEn": "They will be waited on by eternal youths. If you saw them, you would think they were scattered pearls.",
    "meta": {
      "page": 579,
      "juz": 29,
      "hizb": 58,
      "hizbQuarter": 232,
      "sajda": false
    }
  },
  {
    "surahNo": 76,
    "ayahNo": 20,
    "ayahArV1": "وَإِذَا رَأَيْتَ ثَمَّ رَأَيْتَ نَعِيمًا وَمُلْكًا كَبِيرًا",
    "ayahArV2": "واذا رايت ثم رايت نعيما وملكا كبيرا",
    "ayahEn": "And if you looked around, you would see ˹indescribable˺ bliss and a vast kingdom.",
    "meta": {
      "page": 579,
      "juz": 29,
      "hizb": 58,
      "hizbQuarter": 232,
      "sajda": false
    }
  },
  {
    "surahNo": 76,
    "ayahNo": 21,
    "ayahArV1": "عَـٰلِيَهُمْ ثِيَابُ سُندُسٍ خُضْرٌ وَإِسْتَبْرَقٌ ۖ وَحُلُّوٓا۟ أَسَاوِرَ مِن فِضَّةٍ وَسَقَىٰهُمْ رَبُّهُمْ شَرَابًا طَهُورًا",
    "ayahArV2": "عاليهم ثياب سندس خضر واستبرق وحلوا اساور من فضة وسقاهم ربهم شرابا طهورا",
    "ayahEn": "The virtuous will be ˹dressed˺ in garments of fine green silk and rich brocade, and adorned with bracelets of silver, and their Lord will give them a purifying drink.",
    "meta": {
      "page": 579,
      "juz": 29,
      "hizb": 58,
      "hizbQuarter": 232,
      "sajda": false
    }
  },
  {
    "surahNo": 76,
    "ayahNo": 22,
    "ayahArV1": "إِنَّ هَـٰذَا كَانَ لَكُمْ جَزَآءً وَكَانَ سَعْيُكُم مَّشْكُورًا",
    "ayahArV2": "ان هذا كان لكم جزاء وكان سعيكم مشكورا",
    "ayahEn": "˹And they will be told,˺ “All this is surely a reward for you. Your striving has been appreciated.”",
    "meta": {
      "page": 579,
      "juz": 29,
      "hizb": 58,
      "hizbQuarter": 232,
      "sajda": false
    }
  },
  {
    "surahNo": 76,
    "ayahNo": 23,
    "ayahArV1": "إِنَّا نَحْنُ نَزَّلْنَا عَلَيْكَ ٱلْقُرْءَانَ تَنزِيلًا",
    "ayahArV2": "انا نحن نزلنا عليك القران تنزيلا",
    "ayahEn": "Indeed, it is We Who have revealed the Quran to you ˹O Prophet˺ in stages.",
    "meta": {
      "page": 579,
      "juz": 29,
      "hizb": 58,
      "hizbQuarter": 232,
      "sajda": false
    }
  },
  {
    "surahNo": 76,
    "ayahNo": 24,
    "ayahArV1": "فَٱصْبِرْ لِحُكْمِ رَبِّكَ وَلَا تُطِعْ مِنْهُمْ ءَاثِمًا أَوْ كَفُورًا",
    "ayahArV2": "فاصبر لحكم ربك ولا تطع منهم اثما او كفورا",
    "ayahEn": "So be patient with your Lord’s decree, and do not yield to any evildoer or ˹staunch˺ disbeliever from among them.",
    "meta": {
      "page": 579,
      "juz": 29,
      "hizb": 58,
      "hizbQuarter": 232,
      "sajda": false
    }
  },
  {
    "surahNo": 76,
    "ayahNo": 25,
    "ayahArV1": "وَٱذْكُرِ ٱسْمَ رَبِّكَ بُكْرَةً وَأَصِيلًا",
    "ayahArV2": "واذكر اسم ربك بكرة واصيلا",
    "ayahEn": "˹Always˺ remember the Name of your Lord morning and evening",
    "meta": {
      "page": 579,
      "juz": 29,
      "hizb": 58,
      "hizbQuarter": 232,
      "sajda": false
    }
  }
]