[
  {
    "surahNo": 86,
    "ayahNo": 1,
    "ayahArV1": "وَٱلسَّمَآءِ وَٱلطَّارِقِ",
    "ayahArV2": "والسماء والطارق",
    "ayahEn": "By the heaven and the nightly star!",
    "meta": {
      "page": 591,
      "juz": 30,
      "hizb": 59,
      "hizbQuarter": 236,
      "sajda": false
    }
  },
  {
    "surahNo": 86,
    "ayahNo": 2,
    "ayahArV1": "وَمَآ أَدْرَىٰكَ مَا ٱلطَّارِقُ",
    "ayahArV2": "وما ادراك ما الطارق",
    "ayahEn": "And what will make you realize what the nightly star is?",
    "meta": {
      "page": 591,
      "juz": 30,
      "hizb": 59,
      "hizbQuarter": 236,
      "sajda": false
    }
  },
  {
    "surahNo": 86,
    "ayahNo": 3,
    "ayahArV1": "ٱلنَّجْمُ ٱلثَّاقِبُ",
    "ayahArV2": "النجم الثاقب",
    "ayahEn": "˹It is˺ the star of piercing brightness.",
    "meta": {
      "page": 591,
      "juz": 30,
      "hizb": 59,
      "hizbQuarter": 236,
      "sajda": false
    }
  },
  {
    "surahNo": 86,
    "ayahNo": 4,
    "ayahArV1": "إِن كُلُّ نَفْسٍ لَّمَّا عَلَيْهَا حَافِظٌ",
    "ayahArV2": "ان كل نفس لما عليها حافظ",
    "ayahEn": "There is no soul without a vigilant angel ˹recording everything˺.",
    "meta": {
      "page": 591,
      "juz": 30,
      "hizb": 59,
      "hizbQuarter": 236,
      "sajda": false
    }
  },
  {
    "surahNo": 86,
    "ayahNo": 5,
    "ayahArV1": "فَلْيَنظُرِ ٱلْإِنسَـٰنُ مِمَّ خُلِقَ",
    "ayahArV2": "فلينظر الانسان مم خلق",
    "ayahEn": "Let people then consider what they were created from!",
    "meta": {
      "page": 591,
      "juz": 30,
      "hizb": 59,
      "hizbQuarter": 236,
      "sajda": false
    }
  },
  {
    "surahNo": 86,
    "ayahNo": 6,
    "ayahArV1": "خُلِقَ مِن مَّآءٍ دَافِقٍ",
    "ayahArV2": "خلق من ماء دافق",
    "ayahEn": "˹They were˺ created from a spurting fluid",
    "meta": {
      "page": 591,
      "juz": 30,
      "hizb": 59,
      "hizbQuarter": 236,
      "sajda": false
    }
  },
  {
    "surahNo": 86,
    "ayahNo": 7,
    "ayahArV1": "يَخْرُجُ مِنۢ بَيْنِ ٱلصُّلْبِ وَٱلتَّرَآئِبِ",
    "ayahArV2": "يخرج من بين الصلب والترائب",
    "ayahEn": "stemming from between the backbone and the ribcage.",
    "meta": {
      "page": 591,
      "juz": 30,
      "hizb": 59,
      "hizbQuarter": 236,
      "sajda": false
    }
  },
  {
    "surahNo": 86,
    "ayahNo": 8,
    "ayahArV1": "إِنَّهُۥ عَلَىٰ رَجْعِهِۦ لَقَادِرٌ",
    "ayahArV2": "انه على رجعه لقادر",
    "ayahEn": "Surely He is fully capable of bringing them back ˹to life˺",
    "meta": {
      "page": 591,
      "juz": 30,
      "hizb": 59,
      "hizbQuarter": 236,
      "sajda": false
    }
  },
  {
    "surahNo": 86,
    "ayahNo": 9,
    "ayahArV1": "يَوْمَ تُبْلَى ٱلسَّرَآئِرُ",
    "ayahArV2": "يوم تبلى السرائر",
    "ayahEn": "on the Day all secrets will be disclosed.",
    "meta": {
      "page": 591,
      "juz": 30,
      "hizb": 59,
      "hizbQuarter": 236,
      "sajda": false
    }
  },
  {
    "surahNo": 86,
    "ayahNo": 10,
    "ayahArV1": "فَمَا لَهُۥ مِن قُوَّةٍ وَلَا نَاصِرٍ",
    "ayahArV2": "فما له من قوة ولا ناصر",
    "ayahEn": "Then one will have neither power nor ˹any˺ helper.",
    "meta": {
      "page": 591,
      "juz": 30,
      "hizb": 59,
      "hizbQuarter": 236,
      "sajda": false
    }
  },
  {
    "surahNo": 86,
    "ayahNo": 11,
    "ayahArV1": "وَٱلسَّمَآءِ ذَاتِ ٱلرَّجْعِ",
    "ayahArV2": "والسماء ذات الرجع",
    "ayahEn": "By the sky with its recurring cycles",
    "meta": {
      "page": 591,
      "juz": 30,
      "hizb": 59,
      "hizbQuarter": 236,
      "sajda": false
    }
  },
  {
    "surahNo": 86,
    "ayahNo": 12,
    "ayahArV1": "وَٱلْأَرْضِ ذَاتِ ٱلصَّدْعِ",
    "ayahArV2": "والارض ذات الصدع",
    "ayahEn": "and the earth with its sprouting plants!",
    "meta": {
      "page": 591,
      "juz": 30,
      "hizb": 59,
      "hizbQuarter": 236,
      "sajda": false
    }
  },
  {
    "surahNo": 86,
    "ayahNo": 13,
    "ayahArV1": "إِنَّهُۥ لَقَوْلٌ فَصْلٌ",
    "ayahArV2": "انه لقول فصل",
    "ayahEn": "Surely this ˹Quran˺ is a decisive word",
    "meta": {
      "page": 591,
      "juz": 30,
      "hizb": 59,
      "hizbQuarter": 236,
      "sajda": false
    }
  },
  {
    "surahNo": 86,
    "ayahNo": 14,
    "ayahArV1": "وَمَا هُوَ بِٱلْهَزْلِ",
    "ayahArV2": "وما هو بالهزل",
    "ayahEn": "and is not to be taken lightly.",
    "meta": {
      "page": 591,
      "juz": 30,
      "hizb": 59,
      "hizbQuarter": 236,
      "sajda": false
    }
  },
  {
    "surahNo": 86,
    "ayahNo": 15,
    "ayahArV1": "إِنَّهُمْ يَكِيدُونَ كَيْدًا",
    "ayahArV2": "انهم يكيدون كيدا",
    "ayahEn": "They are certainly devising ˹evil˺ plans",
    "meta": {
      "page": 591,
      "juz": 30,
      "hizb": 59,
      "hizbQuarter": 236,
      "sajda": false
    }
  },
  {
    "surahNo": 86,
    "ayahNo": 16,
    "ayahArV1": "وَأَكِيدُ كَيْدًا",
    "ayahArV2": "واكيد كيدا",
    "ayahEn": "but I too am planning.",
    "meta": {
      "page": 591,
      "juz": 30,
      "hizb": 59,
      "hizbQuarter": 236,
      "sajda": false
    }
  },
  {
    "surahNo": 86,
    "ayahNo": 17,
    "ayahArV1": "فَمَهِّلِ ٱلْكَـٰفِرِينَ أَمْهِلْهُمْ رُوَيْدًۢا",
    "ayahArV2": "فمهل الكافرين امهلهم رويدا",
    "ayahEn": "So bear with the disbelievers ˹O Prophet˺. Let them be for ˹just˺ a little while.",
    "meta": {
      "page": 591,
      "juz": 30,
      "hizb": 59,
      "hizbQuarter": 236,
      "sajda": false
    }
  },
  {
    "surahNo": 87,
    "ayahNo": 1,
    "ayahArV1": "سَبِّحِ ٱسْمَ رَبِّكَ ٱلْأَعْلَى",
    "ayahArV2": "سبح اسم ربك الاعلى",
    "ayahEn": "Glorify the Name of your Lord, the Most High",
    "meta": {
      "page": 591,
      "juz": 30,
      "hizb": 60,
      "hizbQuarter": 237,
      "sajda": false
    }
  },
  {
    "surahNo": 87,
    "ayahNo": 2,
    "ayahArV1": "ٱلَّذِى خَلَقَ فَسَوَّىٰ",
    "ayahArV2": "الذي خلق فسوى",
    "ayahEn": "Who created and ˹perfectly˺ fashioned ˹all˺",
    "meta": {
      "page": 591,
      "juz": 30,
      "hizb": 60,
      "hizbQuarter": 237,
      "sajda": false
    }
  },
  {
    "surahNo": 87,
    "ayahNo": 3,
    "ayahArV1": "وَٱلَّذِى قَدَّرَ فَهَدَىٰ",
    "ayahArV2": "والذي قدر فهدى",
    "ayahEn": "and Who ordained precisely and inspired accordingly",
    "meta": {
      "page": 591,
      "juz": 30,
      "hizb": 60,
      "hizbQuarter": 237,
      "sajda": false
    }
  },
  {
    "surahNo": 87,
    "ayahNo": 4,
    "ayahArV1": "وَٱلَّذِىٓ أَخْرَجَ ٱلْمَرْعَىٰ",
    "ayahArV2": "والذي اخرج المرعى",
    "ayahEn": "and Who brings forth ˹green˺ pasture",
    "meta": {
      "page": 591,
      "juz": 30,
      "hizb": 60,
      "hizbQuarter": 237,
      "sajda": false
    }
  },
  {
    "surahNo": 87,
    "ayahNo": 5,
    "ayahArV1": "فَجَعَلَهُۥ غُثَآءً أَحْوَىٰ",
    "ayahArV2": "فجعله غثاء احوى",
    "ayahEn": "then reduces it to withered chaff.",
    "meta": {
      "page": 591,
      "juz": 30,
      "hizb": 60,
      "hizbQuarter": 237,
      "sajda": false
    }
  },
  {
    "surahNo": 87,
    "ayahNo": 6,
    "ayahArV1": "سَنُقْرِئُكَ فَلَا تَنسَىٰٓ",
    "ayahArV2": "سنقرئك فلا تنسى",
    "ayahEn": "We will have you recite ˹the Quran, O  Prophet,˺ so you will not forget ˹any of it˺",
    "meta": {
      "page": 591,
      "juz": 30,
      "hizb": 60,
      "hizbQuarter": 237,
      "sajda": false
    }
  },
  {
    "surahNo": 87,
    "ayahNo": 7,
    "ayahArV1": "إِلَّا مَا شَآءَ ٱللَّهُ ۚ إِنَّهُۥ يَعْلَمُ ٱلْجَهْرَ وَمَا يَخْفَىٰ",
    "ayahArV2": "الا ما شاء الله انه يعلم الجهر وما يخفى",
    "ayahEn": "unless Allah wills otherwise. He surely knows what is open and what is hidden.",
    "meta": {
      "page": 591,
      "juz": 30,
      "hizb": 60,
      "hizbQuarter": 237,
      "sajda": false
    }
  },
  {
    "surahNo": 87,
    "ayahNo": 8,
    "ayahArV1": "وَنُيَسِّرُكَ لِلْيُسْرَىٰ",
    "ayahArV2": "ونيسرك لليسرى",
    "ayahEn": "We will facilitate for you the Way of Ease.",
    "meta": {
      "page": 591,
      "juz": 30,
      "hizb": 60,
      "hizbQuarter": 237,
      "sajda": false
    }
  },
  {
    "surahNo": 87,
    "ayahNo": 9,
    "ayahArV1": "فَذَكِّرْ إِن نَّفَعَتِ ٱلذِّكْرَىٰ",
    "ayahArV2": "فذكر ان نفعت الذكرى",
    "ayahEn": "So ˹always˺ remind ˹with the Quran˺—˹even˺ if the reminder is beneficial ˹only to some˺.",
    "meta": {
      "page": 591,
      "juz": 30,
      "hizb": 60,
      "hizbQuarter": 237,
      "sajda": false
    }
  },
  {
    "surahNo": 87,
    "ayahNo": 10,
    "ayahArV1": "سَيَذَّكَّرُ مَن يَخْشَىٰ",
    "ayahArV2": "سيذكر من يخشى",
    "ayahEn": "Those in awe ˹of Allah˺ will be mindful ˹of it˺.",
    "meta": {
      "page": 591,
      "juz": 30,
      "hizb": 60,
      "hizbQuarter": 237,
      "sajda": false
    }
  },
  {
    "surahNo": 87,
    "ayahNo": 11,
    "ayahArV1": "وَيَتَجَنَّبُهَا ٱلْأَشْقَى",
    "ayahArV2": "ويتجنبها الاشقى",
    "ayahEn": "But it will be shunned by the most wretched",
    "meta": {
      "page": 591,
      "juz": 30,
      "hizb": 60,
      "hizbQuarter": 237,
      "sajda": false
    }
  },
  {
    "surahNo": 87,
    "ayahNo": 12,
    "ayahArV1": "ٱلَّذِى يَصْلَى ٱلنَّارَ ٱلْكُبْرَىٰ",
    "ayahArV2": "الذي يصلى النار الكبرى",
    "ayahEn": "who will burn in the greatest Fire",
    "meta": {
      "page": 591,
      "juz": 30,
      "hizb": 60,
      "hizbQuarter": 237,
      "sajda": false
    }
  },
  {
    "surahNo": 87,
    "ayahNo": 13,
    "ayahArV1": "ثُمَّ لَا يَمُوتُ فِيهَا وَلَا يَحْيَىٰ",
    "ayahArV2": "ثم لا يموت فيها ولا يحيى",
    "ayahEn": "where they will not ˹be able to˺ live or die.",
    "meta": {
      "page": 591,
      "juz": 30,
      "hizb": 60,
      "hizbQuarter": 237,
      "sajda": false
    }
  },
  {
    "surahNo": 87,
    "ayahNo": 14,
    "ayahArV1": "قَدْ أَفْلَحَ مَن تَزَكَّىٰ",
    "ayahArV2": "قد افلح من تزكى",
    "ayahEn": "Successful indeed are those who purify themselves",
    "meta": {
      "page": 591,
      "juz": 30,
      "hizb": 60,
      "hizbQuarter": 237,
      "sajda": false
    }
  },
  {
    "surahNo": 87,
    "ayahNo": 15,
    "ayahArV1": "وَذَكَرَ ٱسْمَ رَبِّهِۦ فَصَلَّىٰ",
    "ayahArV2": "وذكر اسم ربه فصلى",
    "ayahEn": "remember the Name of their Lord, and pray.",
    "meta": {
      "page": 591,
      "juz": 30,
      "hizb": 60,
      "hizbQuarter": 237,
      "sajda": false
    }
  }
]